{
  "slug": "birth-of-writing",
  "title": "The Birth of Writing",
  "topic": "culture",
  "reading_time": "2 min",
  "puzzle": "Why did humans invent writing after speaking for so much longer?",
  "insight": "Writing emerged when societies needed durable records for trade, law, and administration. Once language could be stored outside the mind, knowledge could travel farther.",
  "key_ideas": [
    "Early writing often served recordkeeping.",
    "Written symbols let information survive beyond one speaker.",
    "Writing changed memory, power, and education."
  ],
  "mind_blower": "Writing gave humans a way to think across time by leaving messages for people they would never meet.",
  "next_curiosity": "If writing transformed memory, how did it change who controlled knowledge?",
  "next_lessons": [
    "why-humans-sing",
    "why-humans-dance"
  ],
  "narration_text": "Why did humans invent writing after speaking for so much longer? Writing emerged when societies needed durable records for trade, law, and administration. Once language could be stored outside the mind, knowledge could travel farther. Early writing often served recordkeeping. Written symbols let information survive beyond one speaker. Writing changed memory, power, and education. Writing gave humans a way to think across time by leaving messages for people they would never meet. If writing transformed memory, how did it change who controlled knowledge?"
}
